sdf_loss/DiSCoLoss.py
sdf_loss/DiceLoss.py
sdf_loss/SDFWeightedBCELoss.py
sdf_loss/SDFWeightedDiceLoss.py
sdf_loss/__init__.py
sdf_loss/utils.py
sdf_loss-0.1.1.dist-info/METADATA
sdf_loss-0.1.1.dist-info/WHEEL
sdf_loss-0.1.1.dist-info/licenses/LICENSE
sdf_loss-0.1.1.dist-info/RECORD
