Metadata-Version: 2.4
Name: sdf-loss
Version: 0.1.1
Summary: Signed Distance Function based loss functions for deep learning semantic segmentation to miss fewer instances.
Author-email: Harald <harald.lykke.joakimsen@gmail.com>
License: MIT License
License-File: LICENSE
Keywords: deep learning,loss function,pytorch,sdf,semantic segmentation
Classifier: Development Status :: 3 - Alpha
Classifier: Intended Audience :: Developers
Classifier: Intended Audience :: Science/Research
Classifier: License :: OSI Approved :: MIT License
Classifier: Programming Language :: Python :: 3
Classifier: Programming Language :: Python :: 3.10
Classifier: Programming Language :: Python :: 3.11
Classifier: Programming Language :: Python :: 3.12
Classifier: Programming Language :: Python :: 3.13
Classifier: Topic :: Scientific/Engineering :: Artificial Intelligence
Classifier: Topic :: Software Development :: Libraries :: Python Modules
Requires-Python: >=3.10
Requires-Dist: numpy>=1.20.0
Requires-Dist: scikit-image>=0.19.0
Requires-Dist: scipy>=1.7.0
Requires-Dist: torch>=1.10.0
Provides-Extra: dev
Requires-Dist: pytest>=7.0.0; extra == 'dev'
Requires-Dist: ruff>=0.14.7; extra == 'dev'
